ShejiaoMeitiWajueChuyiFix1/README.md
ShejiaoMeitiWajueChuyiFix1/__init__.py
ShejiaoMeitiWajueChuyiFix1/__main__.py
ShejiaoMeitiWajueChuyiFix1/file.epub
ShejiaoMeitiWajueChuyiFix1/index.html
ShejiaoMeitiWajueChuyiFix1/css/__init__.py
ShejiaoMeitiWajueChuyiFix1/css/annotations.css
ShejiaoMeitiWajueChuyiFix1/css/main.css
ShejiaoMeitiWajueChuyiFix1/css/normalize.css
ShejiaoMeitiWajueChuyiFix1/css/popup.css
ShejiaoMeitiWajueChuyiFix1/font/__init__.py
ShejiaoMeitiWajueChuyiFix1/font/fontello.eot
ShejiaoMeitiWajueChuyiFix1/font/fontello.svg
ShejiaoMeitiWajueChuyiFix1/font/fontello.ttf
ShejiaoMeitiWajueChuyiFix1/font/fontello.woff
ShejiaoMeitiWajueChuyiFix1/img/__init__.py
ShejiaoMeitiWajueChuyiFix1/img/annotator-glyph-sprite.png
ShejiaoMeitiWajueChuyiFix1/img/annotator-icon-sprite.png
ShejiaoMeitiWajueChuyiFix1/img/apple-touch-icon.png
ShejiaoMeitiWajueChuyiFix1/img/cancelfullscreen.png
ShejiaoMeitiWajueChuyiFix1/img/close.png
ShejiaoMeitiWajueChuyiFix1/img/fullscreen.png
ShejiaoMeitiWajueChuyiFix1/img/loader.gif
ShejiaoMeitiWajueChuyiFix1/img/menu-icon.png
ShejiaoMeitiWajueChuyiFix1/img/save.png
ShejiaoMeitiWajueChuyiFix1/img/saved.png
ShejiaoMeitiWajueChuyiFix1/img/settings-s.png
ShejiaoMeitiWajueChuyiFix1/img/settings.png
ShejiaoMeitiWajueChuyiFix1/img/star.png
ShejiaoMeitiWajueChuyiFix1/js/__init__.py
ShejiaoMeitiWajueChuyiFix1/js/epub.js
ShejiaoMeitiWajueChuyiFix1/js/epub.min.js
ShejiaoMeitiWajueChuyiFix1/js/epub.min.map
ShejiaoMeitiWajueChuyiFix1/js/hooks.min.js
ShejiaoMeitiWajueChuyiFix1/js/hooks.min.map
ShejiaoMeitiWajueChuyiFix1/js/reader.js
ShejiaoMeitiWajueChuyiFix1/js/reader.js.map
ShejiaoMeitiWajueChuyiFix1/js/reader.min.js
ShejiaoMeitiWajueChuyiFix1/js/reader.min.map
ShejiaoMeitiWajueChuyiFix1/js/hooks/__init__.py
ShejiaoMeitiWajueChuyiFix1/js/hooks/extensions/__init__.py
ShejiaoMeitiWajueChuyiFix1/js/hooks/extensions/highlight.js
ShejiaoMeitiWajueChuyiFix1/js/libs/__init__.py
ShejiaoMeitiWajueChuyiFix1/js/libs/jquery.min.js
shejiao_meiti_wajue_chuyi_fix1-2025.3.24.0.dist-info/METADATA
shejiao_meiti_wajue_chuyi_fix1-2025.3.24.0.dist-info/WHEEL
shejiao_meiti_wajue_chuyi_fix1-2025.3.24.0.dist-info/entry_points.txt
shejiao_meiti_wajue_chuyi_fix1-2025.3.24.0.dist-info/top_level.txt
shejiao_meiti_wajue_chuyi_fix1-2025.3.24.0.dist-info/RECORD
